Metadata-Version: 1.0
Name: gb-julio-distributions
Version: 0.1
Summary: Gaussian distributions
Home-page: UNKNOWN
Author: Julio Mastrodomenico
Author-email: UNKNOWN
License: UNKNOWN
Platform: UNKNOWN
